<?xml version="1.0" encoding="utf-8"?>
<GameData>
	<LocalizedText>
		<!--Babylon-->
		<Replace Language='en_US' Tag="LOC_CITIZEN_VIETNAM_MALE_1">
			<Text>Nam</Text>
		</Replace>
		<Replace Language='en_US' Tag="LOC_CITIZEN_VIETNAM_MALE_2">
			<Text>Văn</Text>
		</Replace>
		<Replace Language='en_US' Tag="LOC_CITIZEN_VIETNAM_MALE_3">
			<Text>Dũng</Text>
		</Replace>
		<Replace Language='en_US' Tag="LOC_CITIZEN_VIETNAM_MALE_4">
			<Text>Quang</Text>
		</Replace>
		<Replace Language='en_US' Tag="LOC_CITIZEN_VIETNAM_MALE_5">
			<Text>Hồ</Text>
		</Replace>
		<Replace Language='en_US' Tag="LOC_CITIZEN_VIETNAM_MALE_6">
			<Text>Giáp</Text>
		</Replace>
		<Replace Language='en_US' Tag="LOC_CITIZEN_VIETNAM_MALE_7">
			<Text>Hiến</Text>
		</Replace>
		<Replace Language='en_US' Tag="LOC_CITIZEN_VIETNAM_MALE_8">
			<Text>Tông</Text>
		</Replace>
		<Replace Language='en_US' Tag="LOC_CITIZEN_VIETNAM_MALE_9">
			<Text>Túc</Text>
		</Replace>
		<Replace Language='en_US' Tag="LOC_CITIZEN_VIETNAM_MALE_10">
			<Text>Mục</Text>
		</Replace>
		<Replace Language='en_US' Tag="LOC_CITIZEN_VIETNAM_FEMALE_1">
			<Text>Lan</Text>
		</Replace>
		<Replace Language='en_US' Tag="LOC_CITIZEN_VIETNAM_FEMALE_2">
			<Text>Chiêu</Text>
		</Replace>
		<Replace Language='en_US' Tag="LOC_CITIZEN_VIETNAM_FEMALE_3">
			<Text>Thị</Text>
		</Replace>
		<Replace Language='en_US' Tag="LOC_CITIZEN_VIETNAM_FEMALE_4">
			<Text>Khoa</Text>
		</Replace>
		<Replace Language='en_US' Tag="LOC_CITIZEN_VIETNAM_FEMALE_5">
			<Text>Hoàng</Text>
		</Replace>
		<Replace Language='en_US' Tag="LOC_CITIZEN_VIETNAM_FEMALE_6">
			<Text>Từ</Text>
		</Replace>
		<Replace Language='en_US' Tag="LOC_CITIZEN_VIETNAM_FEMALE_7">
			<Text>Phật</Text>
		</Replace>
		<Replace Language='en_US' Tag="LOC_CITIZEN_VIETNAM_FEMALE_8">
			<Text>Kim</Text>
		</Replace>
		<Replace Language='en_US' Tag="LOC_CITIZEN_VIETNAM_FEMALE_9">
			<Text>Trắc</Text>
		</Replace>
		<Replace Language='en_US' Tag="LOC_CITIZEN_VIETNAM_FEMALE_10">
			<Text>Nhị</Text>
		</Replace>
		<Replace Language='en_US' Tag="LOC_CITIZEN_VIETNAM_MODERN_MALE_1">
			<Text>Định</Text>
		</Replace>
		<Replace Language='en_US' Tag="LOC_CITIZEN_VIETNAM_MODERN_MALE_2">
			<Text>Dương</Text>
		</Replace>
		<Replace Language='en_US' Tag="LOC_CITIZEN_VIETNAM_MODERN_MALE_3">
			<Text>Công </Text>
		</Replace>
		<Replace Language='en_US' Tag="LOC_CITIZEN_VIETNAM_MODERN_MALE_4">
			<Text>Giang</Text>
		</Replace>
		<Replace Language='en_US' Tag="LOC_CITIZEN_VIETNAM_MODERN_MALE_5">
			<Text>Hà</Text>
		</Replace>
		<Replace Language='en_US' Tag="LOC_CITIZEN_VIETNAM_MODERN_MALE_6">
			<Text>Đức</Text>
		</Replace>
		<Replace Language='en_US' Tag="LOC_CITIZEN_VIETNAM_MODERN_MALE_7">
			<Text>Huy</Text>
		</Replace>
		<Replace Language='en_US' Tag="LOC_CITIZEN_VIETNAM_MODERN_MALE_8">
			<Text>Nam</Text>
		</Replace>
		<Replace Language='en_US' Tag="LOC_CITIZEN_VIETNAM_MODERN_MALE_9">
			<Text>Nguyên</Text>
		</Replace>
		<Replace Language='en_US' Tag="LOC_CITIZEN_VIETNAM_MODERN_MALE_10">
			<Text>Quân</Text>
		</Replace>
		<Replace Language='en_US' Tag="LOC_CITIZEN_VIETNAM_MODERN_FEMALE_1">
			<Text>Bạch</Text>
		</Replace>
		<Replace Language='en_US' Tag="LOC_CITIZEN_VIETNAM_MODERN_FEMALE_2">
			<Text>Binh</Text>
		</Replace>
		<Replace Language='en_US' Tag="LOC_CITIZEN_VIETNAM_MODERN_FEMALE_3">
			<Text>Trà</Text>
		</Replace>
		<Replace Language='en_US' Tag="LOC_CITIZEN_VIETNAM_MODERN_FEMALE_4">
			<Text>Chinh</Text>
		</Replace>
		<Replace Language='en_US' Tag="LOC_CITIZEN_VIETNAM_MODERN_FEMALE_5">
			<Text>Huệ</Text>
		</Replace>
		<Replace Language='en_US' Tag="LOC_CITIZEN_VIETNAM_MODERN_FEMALE_6">
			<Text>Hồng</Text>
		</Replace>
		<Replace Language='en_US' Tag="LOC_CITIZEN_VIETNAM_MODERN_FEMALE_7">
			<Text>Linh</Text>
		</Replace>
		<Replace Language='en_US' Tag="LOC_CITIZEN_VIETNAM_MODERN_FEMALE_8">
			<Text>Quỳnh</Text>
		</Replace>
		<Replace Language='en_US' Tag="LOC_CITIZEN_VIETNAM_MODERN_FEMALE_9">
			<Text>Nguyệt</Text>
		</Replace>
		<Replace Language='en_US' Tag="LOC_CITIZEN_VIETNAM_MODERN_FEMALE_10">
			<Text>Ngọc</Text>
		</Replace>
	</LocalizedText>
</GameData>
